{
    "asset": {
        "format": "jpg",
        "id": "08a6c8927970372f1a5bec9ec4d79287",
        "name": "dynamite_5094.jpg",
        "path": "file:/Users/choumasateru/programming/dynamite/dynamite_imgs/dynamite_5094.jpg",
        "size": {
            "width": 1920,
            "height": 1080
        },
        "state": 2,
        "type": 1
    },
    "regions": [
        {
            "id": "B_jOwfelx",
            "type": "RECTANGLE",
            "tags": [
                "J-HOPE"
            ],
            "boundingBox": {
                "height": 93.02724483095366,
                "width": 90.96614330746847,
                "left": 1792.8053012851599,
                "top": 412.50566995554954
            },
            "points": [
                {
                    "x": 1792.8053012851599,
                    "y": 412.50566995554954
                },
                {
                    "x": 1883.7714445926285,
                    "y": 412.50566995554954
                },
                {
                    "x": 1883.7714445926285,
                    "y": 505.5329147865032
                },
                {
                    "x": 1792.8053012851599,
                    "y": 505.5329147865032
                }
            ]
        },
        {
            "id": "aj5bVA1MQ",
            "type": "RECTANGLE",
            "tags": [
                "JIMIN"
            ],
            "boundingBox": {
                "height": 123.97215113146551,
                "width": 111.14012487875848,
                "left": 1422.0354176770124,
                "top": 376.6476587755927
            },
            "points": [
                {
                    "x": 1422.0354176770124,
                    "y": 376.6476587755927
                },
                {
                    "x": 1533.175542555771,
                    "y": 376.6476587755927
                },
                {
                    "x": 1533.175542555771,
                    "y": 500.6198099070582
                },
                {
                    "x": 1422.0354176770124,
                    "y": 500.6198099070582
                }
            ]
        },
        {
            "id": "pPRSI_eE2",
            "type": "RECTANGLE",
            "tags": [
                "RM"
            ],
            "boundingBox": {
                "height": 104.20960314520474,
                "width": 102.03962324199806,
                "left": 1109.562621241513,
                "top": 348.0729012324892
            },
            "points": [
                {
                    "x": 1109.562621241513,
                    "y": 348.0729012324892
                },
                {
                    "x": 1211.6022444835112,
                    "y": 348.0729012324892
                },
                {
                    "x": 1211.6022444835112,
                    "y": 452.28250437769395
                },
                {
                    "x": 1109.562621241513,
                    "y": 452.28250437769395
                }
            ]
        },
        {
            "id": "cV8B4aryh",
            "type": "RECTANGLE",
            "tags": [
                "V"
            ],
            "boundingBox": {
                "height": 138.9804792733028,
                "width": 129.10550284917556,
                "left": 896.9085687439378,
                "top": 362.78334834657863
            },
            "points": [
                {
                    "x": 896.9085687439378,
                    "y": 362.78334834657863
                },
                {
                    "x": 1026.0140715931134,
                    "y": 362.78334834657863
                },
                {
                    "x": 1026.0140715931134,
                    "y": 501.76382761988145
                },
                {
                    "x": 896.9085687439378,
                    "y": 501.76382761988145
                }
            ]
        },
        {
            "id": "ar31GYcb7",
            "type": "RECTANGLE",
            "tags": [
                "SUGA"
            ],
            "boundingBox": {
                "height": 99.34570943898167,
                "width": 90.98808044374394,
                "left": 735.1582201745878,
                "top": 425.0227534853179
            },
            "points": [
                {
                    "x": 735.1582201745878,
                    "y": 425.0227534853179
                },
                {
                    "x": 826.1463006183317,
                    "y": 425.0227534853179
                },
                {
                    "x": 826.1463006183317,
                    "y": 524.3684629242996
                },
                {
                    "x": 735.1582201745878,
                    "y": 524.3684629242996
                }
            ]
        },
        {
            "id": "2J1Lzu7W2",
            "type": "RECTANGLE",
            "tags": [
                "JIN"
            ],
            "boundingBox": {
                "height": 103.9107560782597,
                "width": 100.23918677255092,
                "left": 488.9776309408341,
                "top": 422.2921016298491
            },
            "points": [
                {
                    "x": 488.9776309408341,
                    "y": 422.2921016298491
                },
                {
                    "x": 589.216817713385,
                    "y": 422.2921016298491
                },
                {
                    "x": 589.216817713385,
                    "y": 526.2028577081088
                },
                {
                    "x": 488.9776309408341,
                    "y": 526.2028577081088
                }
            ]
        },
        {
            "id": "Vwl3hsFbn",
            "type": "RECTANGLE",
            "tags": [
                "KOOK"
            ],
            "boundingBox": {
                "height": 97.18808930495689,
                "width": 105.7538475236421,
                "left": 125.62627871908342,
                "top": 372.3065059267241
            },
            "points": [
                {
                    "x": 125.62627871908342,
                    "y": 372.3065059267241
                },
                {
                    "x": 231.3801262427255,
                    "y": 372.3065059267241
                },
                {
                    "x": 231.3801262427255,
                    "y": 469.49459523168105
                },
                {
                    "x": 125.62627871908342,
                    "y": 469.49459523168105
                }
            ]
        }
    ],
    "version": "2.2.0"
}