{
    "asset": {
        "format": "jpg",
        "id": "0adbadede3132d8c0d708c33755bac11",
        "name": "dynamite_3303.jpg",
        "path": "file:/Users/choumasateru/programming/dynamite/dynamite_imgs/dynamite_3303.jpg",
        "size": {
            "width": 1920,
            "height": 1080
        },
        "state": 2,
        "type": 1
    },
    "regions": [
        {
            "id": "LrrVMaiTC",
            "type": "RECTANGLE",
            "tags": [
                "KOOK"
            ],
            "boundingBox": {
                "height": 119.98030669113685,
                "width": 110.79947411493696,
                "left": 1116.4123499636275,
                "top": 205.50688224003233
            },
            "points": [
                {
                    "x": 1116.4123499636275,
                    "y": 205.50688224003233
                },
                {
                    "x": 1227.2118240785644,
                    "y": 205.50688224003233
                },
                {
                    "x": 1227.2118240785644,
                    "y": 325.48718893116916
                },
                {
                    "x": 1116.4123499636275,
                    "y": 325.48718893116916
                }
            ]
        },
        {
            "id": "dfMo2Bj_Y",
            "type": "RECTANGLE",
            "tags": [
                "V"
            ],
            "boundingBox": {
                "height": 131.71273908943965,
                "width": 109.1820365543162,
                "left": 939.0751545829291,
                "top": 196.62875471443965
            },
            "points": [
                {
                    "x": 939.0751545829291,
                    "y": 196.62875471443965
                },
                {
                    "x": 1048.2571911372454,
                    "y": 196.62875471443965
                },
                {
                    "x": 1048.2571911372454,
                    "y": 328.3414938038793
                },
                {
                    "x": 939.0751545829291,
                    "y": 328.3414938038793
                }
            ]
        },
        {
            "id": "GhY7Qqek8",
            "type": "RECTANGLE",
            "tags": [
                "JIN"
            ],
            "boundingBox": {
                "height": 96.41423508216594,
                "width": 83.76968280189136,
                "left": 587.3398285948108,
                "top": 284.0847378434806
            },
            "points": [
                {
                    "x": 587.3398285948108,
                    "y": 284.0847378434806
                },
                {
                    "x": 671.1095113967023,
                    "y": 284.0847378434806
                },
                {
                    "x": 671.1095113967023,
                    "y": 380.4989729256465
                },
                {
                    "x": 587.3398285948108,
                    "y": 380.4989729256465
                }
            ]
        },
        {
            "id": "3DBMk40Y7",
            "type": "RECTANGLE",
            "tags": [
                "SUGA"
            ],
            "boundingBox": {
                "height": 94.10142359240301,
                "width": 81.1990027885548,
                "left": 331.40875060620755,
                "top": 291.9340336240571
            },
            "points": [
                {
                    "x": 331.40875060620755,
                    "y": 291.9340336240571
                },
                {
                    "x": 412.60775339476237,
                    "y": 291.9340336240571
                },
                {
                    "x": 412.60775339476237,
                    "y": 386.03545721646014
                },
                {
                    "x": 331.40875060620755,
                    "y": 386.03545721646014
                }
            ]
        },
        {
            "id": "pFrykT0EM",
            "type": "RECTANGLE",
            "tags": [
                "RM"
            ],
            "boundingBox": {
                "height": 88.33354450094289,
                "width": 76.80109003697866,
                "left": 104.47541260002424,
                "top": 266.37792126885773
            },
            "points": [
                {
                    "x": 104.47541260002424,
                    "y": 266.37792126885773
                },
                {
                    "x": 181.2765026370029,
                    "y": 266.37792126885773
                },
                {
                    "x": 181.2765026370029,
                    "y": 354.7114657698006
                },
                {
                    "x": 104.47541260002424,
                    "y": 354.7114657698006
                }
            ]
        }
    ],
    "version": "2.2.0"
}