{
    "asset": {
        "format": "jpg",
        "id": "0c162b9c8f527820aea4710f47f17dd3",
        "name": "dynamite_3807.jpg",
        "path": "file:/Users/choumasateru/programming/dynamite/dynamite_imgs/dynamite_3807.jpg",
        "size": {
            "width": 1920,
            "height": 1080
        },
        "state": 2,
        "type": 1
    },
    "regions": [
        {
            "id": "Tz5PLA6ux",
            "type": "RECTANGLE",
            "tags": [
                "JIN"
            ],
            "boundingBox": {
                "height": 213.02812247440733,
                "width": 163.1754667798254,
                "left": 1410.7640488603297,
                "top": 477.1477850552263
            },
            "points": [
                {
                    "x": 1410.7640488603297,
                    "y": 477.1477850552263
                },
                {
                    "x": 1573.9395156401552,
                    "y": 477.1477850552263
                },
                {
                    "x": 1573.9395156401552,
                    "y": 690.1759075296336
                },
                {
                    "x": 1410.7640488603297,
                    "y": 690.1759075296336
                }
            ]
        },
        {
            "id": "CUoCvW9fE",
            "type": "RECTANGLE",
            "tags": [
                "J-HOPE"
            ],
            "boundingBox": {
                "height": 217.58271316002154,
                "width": 172.99625666828322,
                "left": 1076.6694198593598,
                "top": 532.1492835735453
            },
            "points": [
                {
                    "x": 1076.6694198593598,
                    "y": 532.1492835735453
                },
                {
                    "x": 1249.665676527643,
                    "y": 532.1492835735453
                },
                {
                    "x": 1249.665676527643,
                    "y": 749.7319967335668
                },
                {
                    "x": 1076.6694198593598,
                    "y": 749.7319967335668
                }
            ]
        },
        {
            "id": "dS3EyIRtG",
            "type": "RECTANGLE",
            "tags": [
                "V"
            ],
            "boundingBox": {
                "height": 208.26964069234913,
                "width": 174.7150824442289,
                "left": 832.3640579534432,
                "top": 480.7395187904095
            },
            "points": [
                {
                    "x": 832.3640579534432,
                    "y": 480.7395187904095
                },
                {
                    "x": 1007.0791403976722,
                    "y": 480.7395187904095
                },
                {
                    "x": 1007.0791403976722,
                    "y": 689.0091594827586
                },
                {
                    "x": 832.3640579534432,
                    "y": 689.0091594827586
                }
            ]
        },
        {
            "id": "HNATe_YhK",
            "type": "RECTANGLE",
            "tags": [
                "RM"
            ],
            "boundingBox": {
                "height": 237.08806741648706,
                "width": 176.42595174587777,
                "left": 612.5206489451988,
                "top": 440.69503468480605
            },
            "points": [
                {
                    "x": 612.5206489451988,
                    "y": 440.69503468480605
                },
                {
                    "x": 788.9466006910766,
                    "y": 440.69503468480605
                },
                {
                    "x": 788.9466006910766,
                    "y": 677.7831021012931
                },
                {
                    "x": 612.5206489451988,
                    "y": 677.7831021012931
                }
            ]
        },
        {
            "id": "3HhdEHLX1",
            "type": "RECTANGLE",
            "tags": [
                "SUGA"
            ],
            "boundingBox": {
                "height": 214.04041790140084,
                "width": 198.76534462900096,
                "left": 346.38840476479146,
                "top": 499.37236917429954
            },
            "points": [
                {
                    "x": 346.38840476479146,
                    "y": 499.37236917429954
                },
                {
                    "x": 545.1537493937924,
                    "y": 499.37236917429954
                },
                {
                    "x": 545.1537493937924,
                    "y": 713.4127870757004
                },
                {
                    "x": 346.38840476479146,
                    "y": 713.4127870757004
                }
            ]
        }
    ],
    "version": "2.2.0"
}