{
    "asset": {
        "format": "jpg",
        "id": "390d69a849838b35d2b43f1de228395c",
        "name": "dynamite_3325.jpg",
        "path": "file:/Users/choumasateru/programming/dynamite/dynamite_imgs/dynamite_3325.jpg",
        "size": {
            "width": 1920,
            "height": 1080
        },
        "state": 2,
        "type": 1
    },
    "regions": [
        {
            "id": "q0bvKE5nv",
            "type": "RECTANGLE",
            "tags": [
                "KOOK"
            ],
            "boundingBox": {
                "height": 130.80716258081895,
                "width": 120.20880061833171,
                "left": 1082.1799602934045,
                "top": 204.30410661368535
            },
            "points": [
                {
                    "x": 1082.1799602934045,
                    "y": 204.30410661368535
                },
                {
                    "x": 1202.3887609117362,
                    "y": 204.30410661368535
                },
                {
                    "x": 1202.3887609117362,
                    "y": 335.1112691945043
                },
                {
                    "x": 1082.1799602934045,
                    "y": 335.1112691945043
                }
            ]
        },
        {
            "id": "xKqeaWlmc",
            "type": "RECTANGLE",
            "tags": [
                "V"
            ],
            "boundingBox": {
                "height": 123.23182415140086,
                "width": 104.53136366391853,
                "left": 883.2991331231814,
                "top": 187.02337015086206
            },
            "points": [
                {
                    "x": 883.2991331231814,
                    "y": 187.02337015086206
                },
                {
                    "x": 987.8304967870998,
                    "y": 187.02337015086206
                },
                {
                    "x": 987.8304967870998,
                    "y": 310.2551943022629
                },
                {
                    "x": 883.2991331231814,
                    "y": 310.2551943022629
                }
            ]
        },
        {
            "id": "6CklCr-nN",
            "type": "RECTANGLE",
            "tags": [
                "JIN"
            ],
            "boundingBox": {
                "height": 95.95826458108836,
                "width": 83.26615164282249,
                "left": 542.6210899612026,
                "top": 276.18401468211204
            },
            "points": [
                {
                    "x": 542.6210899612026,
                    "y": 276.18401468211204
                },
                {
                    "x": 625.8872416040252,
                    "y": 276.18401468211204
                },
                {
                    "x": 625.8872416040252,
                    "y": 372.1422792632004
                },
                {
                    "x": 542.6210899612026,
                    "y": 372.1422792632004
                }
            ]
        },
        {
            "id": "9TqFedtzF",
            "type": "RECTANGLE",
            "tags": [
                "SUGA"
            ],
            "boundingBox": {
                "height": 82.6210137728987,
                "width": 85.0646558256547,
                "left": 286.1052111117847,
                "top": 304.76854626885773
            },
            "points": [
                {
                    "x": 286.1052111117847,
                    "y": 304.76854626885773
                },
                {
                    "x": 371.16986693743934,
                    "y": 304.76854626885773
                },
                {
                    "x": 371.16986693743934,
                    "y": 387.38956004175645
                },
                {
                    "x": 286.1052111117847,
                    "y": 387.38956004175645
                }
            ]
        },
        {
            "id": "yrn0hPoix",
            "type": "RECTANGLE",
            "tags": [
                "RM"
            ],
            "boundingBox": {
                "height": 95.8282470703125,
                "width": 79.295615224903,
                "left": 9.130764655067894,
                "top": 279.05746986126076
            },
            "points": [
                {
                    "x": 9.130764655067894,
                    "y": 279.05746986126076
                },
                {
                    "x": 88.4263798799709,
                    "y": 279.05746986126076
                },
                {
                    "x": 88.4263798799709,
                    "y": 374.88571693157326
                },
                {
                    "x": 9.130764655067894,
                    "y": 374.88571693157326
                }
            ]
        }
    ],
    "version": "2.2.0"
}