{
    "asset": {
        "format": "jpg",
        "id": "441f875a04e2171d46b7279aba42ff0c",
        "name": "dynamite_3519.jpg",
        "path": "file:/Users/choumasateru/programming/dynamite/dynamite_imgs/dynamite_3519.jpg",
        "size": {
            "width": 1920,
            "height": 1080
        },
        "state": 2,
        "type": 1
    },
    "regions": [
        {
            "id": "DXASreiP8",
            "type": "RECTANGLE",
            "tags": [
                "SUGA"
            ],
            "boundingBox": {
                "height": 204.96908253636852,
                "width": 59.63036493695441,
                "left": 1860.3696350630455,
                "top": 488.0225451239224
            },
            "points": [
                {
                    "x": 1860.3696350630455,
                    "y": 488.0225451239224
                },
                {
                    "x": 1920,
                    "y": 488.0225451239224
                },
                {
                    "x": 1920,
                    "y": 692.9916276602909
                },
                {
                    "x": 1860.3696350630455,
                    "y": 692.9916276602909
                }
            ]
        },
        {
            "id": "UAUEn1J4O",
            "type": "RECTANGLE",
            "tags": [
                "J-HOPE"
            ],
            "boundingBox": {
                "height": 205.02193056303878,
                "width": 173.27461960475267,
                "left": 1587.3169632032007,
                "top": 436.8913405845905
            },
            "points": [
                {
                    "x": 1587.3169632032007,
                    "y": 436.8913405845905
                },
                {
                    "x": 1760.5915828079533,
                    "y": 436.8913405845905
                },
                {
                    "x": 1760.5915828079533,
                    "y": 641.9132711476293
                },
                {
                    "x": 1587.3169632032007,
                    "y": 641.9132711476293
                }
            ]
        },
        {
            "id": "09EzXw2tP",
            "type": "RECTANGLE",
            "tags": [
                "JIMIN"
            ],
            "boundingBox": {
                "height": 154.16258081896552,
                "width": 152.02412706110573,
                "left": 1232.8225024248302,
                "top": 541.8620689655172
            },
            "points": [
                {
                    "x": 1232.8225024248302,
                    "y": 541.8620689655172
                },
                {
                    "x": 1384.8466294859359,
                    "y": 541.8620689655172
                },
                {
                    "x": 1384.8466294859359,
                    "y": 696.0246497844828
                },
                {
                    "x": 1232.8225024248302,
                    "y": 696.0246497844828
                }
            ]
        },
        {
            "id": "cJ-Y2hdY9",
            "type": "RECTANGLE",
            "tags": [
                "JIN"
            ],
            "boundingBox": {
                "height": 190.12338993467134,
                "width": 146.2083990058196,
                "left": 847.8373545101842,
                "top": 456.89852379108294
            },
            "points": [
                {
                    "x": 847.8373545101842,
                    "y": 456.89852379108294
                },
                {
                    "x": 994.0457535160039,
                    "y": 456.89852379108294
                },
                {
                    "x": 994.0457535160039,
                    "y": 647.0219137257543
                },
                {
                    "x": 847.8373545101842,
                    "y": 647.0219137257543
                }
            ]
        },
        {
            "id": "VWHM8LgAo",
            "type": "RECTANGLE",
            "tags": [
                "JIN"
            ],
            "boundingBox": {
                "height": 162.6091729525862,
                "width": 139.9995642883123,
                "left": 542.6186461869544,
                "top": 460.3222235317888
            },
            "points": [
                {
                    "x": 542.6186461869544,
                    "y": 460.3222235317888
                },
                {
                    "x": 682.6182104752667,
                    "y": 460.3222235317888
                },
                {
                    "x": 682.6182104752667,
                    "y": 622.931396484375
                },
                {
                    "x": 542.6186461869544,
                    "y": 622.931396484375
                }
            ]
        },
        {
            "id": "WD92OcgjH",
            "type": "RECTANGLE",
            "tags": [
                "RM"
            ],
            "boundingBox": {
                "height": 167.16166108230064,
                "width": 145.14493096811347,
                "left": 147.85541760123667,
                "top": 433.3142679148707
            },
            "points": [
                {
                    "x": 147.85541760123667,
                    "y": 433.3142679148707
                },
                {
                    "x": 293.00034856935014,
                    "y": 433.3142679148707
                },
                {
                    "x": 293.00034856935014,
                    "y": 600.4759289971713
                },
                {
                    "x": 147.85541760123667,
                    "y": 600.4759289971713
                }
            ]
        }
    ],
    "version": "2.2.0"
}