{
    "asset": {
        "format": "jpg",
        "id": "5a2525f47071582f07da9483c886c855",
        "name": "dynamite_0271.jpg",
        "path": "file:/Users/choumasateru/programming/dynamite/dynamite_imgs/dynamite_0271.jpg",
        "size": {
            "width": 1920,
            "height": 1080
        },
        "state": 2,
        "type": 1
    },
    "regions": [
        {
            "id": "twjjc5tvt",
            "type": "RECTANGLE",
            "tags": [
                "RM"
            ],
            "boundingBox": {
                "height": 149.13087729357798,
                "width": 135.83361551857584,
                "left": 1381.2536280959753,
                "top": 253.25719878870413
            },
            "points": [
                {
                    "x": 1381.2536280959753,
                    "y": 253.25719878870413
                },
                {
                    "x": 1517.0872436145512,
                    "y": 253.25719878870413
                },
                {
                    "x": 1517.0872436145512,
                    "y": 402.3880760822821
                },
                {
                    "x": 1381.2536280959753,
                    "y": 402.3880760822821
                }
            ]
        },
        {
            "id": "UTSFQKKgI",
            "type": "RECTANGLE",
            "tags": [
                "SUGA"
            ],
            "boundingBox": {
                "height": 151.38551372563074,
                "width": 145.13901654411765,
                "left": 363.5658136609907,
                "top": 321.4236355002867
            },
            "points": [
                {
                    "x": 363.5658136609907,
                    "y": 321.4236355002867
                },
                {
                    "x": 508.70483020510835,
                    "y": 321.4236355002867
                },
                {
                    "x": 508.70483020510835,
                    "y": 472.80914922591745
                },
                {
                    "x": 363.5658136609907,
                    "y": 472.80914922591745
                }
            ]
        },
        {
            "id": "v5l4ghVH-",
            "type": "RECTANGLE",
            "tags": [
                "J-HOPE"
            ],
            "boundingBox": {
                "height": 124.90965228999427,
                "width": 99.73817240712074,
                "left": 1303.4231085526317,
                "top": 359.3909340954702
            },
            "points": [
                {
                    "x": 1303.4231085526317,
                    "y": 359.3909340954702
                },
                {
                    "x": 1403.1612809597523,
                    "y": 359.3909340954702
                },
                {
                    "x": 1403.1612809597523,
                    "y": 484.3005863854645
                },
                {
                    "x": 1303.4231085526317,
                    "y": 484.3005863854645
                }
            ]
        },
        {
            "id": "PdwHaJgs9",
            "type": "RECTANGLE",
            "tags": [
                "JIN"
            ],
            "boundingBox": {
                "height": 141.6543282325115,
                "width": 123.39783281733746,
                "left": 777.4915344427245,
                "top": 339.0862645140482
            },
            "points": [
                {
                    "x": 777.4915344427245,
                    "y": 339.0862645140482
                },
                {
                    "x": 900.8893672600619,
                    "y": 339.0862645140482
                },
                {
                    "x": 900.8893672600619,
                    "y": 480.7405927465597
                },
                {
                    "x": 777.4915344427245,
                    "y": 480.7405927465597
                }
            ]
        },
        {
            "id": "ivA2diIVd",
            "type": "RECTANGLE",
            "tags": [
                "KOOK"
            ],
            "boundingBox": {
                "height": 149.0259528203842,
                "width": 137.37628192724458,
                "left": 1037.717202012384,
                "top": 289.20976607296444
            },
            "points": [
                {
                    "x": 1037.717202012384,
                    "y": 289.20976607296444
                },
                {
                    "x": 1175.0934839396284,
                    "y": 289.20976607296444
                },
                {
                    "x": 1175.0934839396284,
                    "y": 438.23571889334863
                },
                {
                    "x": 1037.717202012384,
                    "y": 438.23571889334863
                }
            ]
        },
        {
            "id": "5PD8953c2",
            "type": "RECTANGLE",
            "tags": [
                "V"
            ],
            "boundingBox": {
                "height": 158.43516834504015,
                "width": 137.06172600619195,
                "left": 630.9181501547988,
                "top": 281.1802922520069
            },
            "points": [
                {
                    "x": 630.9181501547988,
                    "y": 281.1802922520069
                },
                {
                    "x": 767.9798761609907,
                    "y": 281.1802922520069
                },
                {
                    "x": 767.9798761609907,
                    "y": 439.61546059704705
                },
                {
                    "x": 630.9181501547988,
                    "y": 439.61546059704705
                }
            ]
        }
    ],
    "version": "2.2.0"
}