{
    "asset": {
        "format": "jpg",
        "id": "89ca6d75d5a3c2885b96d20f5c30fd79",
        "name": "dynamite_3011.jpg",
        "path": "file:/Users/choumasateru/programming/dynamite/dynamite_imgs/dynamite_3011.jpg",
        "size": {
            "width": 1920,
            "height": 1080
        },
        "state": 2,
        "type": 1
    },
    "regions": [
        {
            "id": "z-7vsJ3b6",
            "type": "RECTANGLE",
            "tags": [
                "KOOK"
            ],
            "boundingBox": {
                "height": 158.12464182962202,
                "width": 138.44992099719101,
                "left": 1365.0709708567415,
                "top": 394.1903083481475
            },
            "points": [
                {
                    "x": 1365.0709708567415,
                    "y": 394.1903083481475
                },
                {
                    "x": 1503.5208918539327,
                    "y": 394.1903083481475
                },
                {
                    "x": 1503.5208918539327,
                    "y": 552.3149501777694
                },
                {
                    "x": 1365.0709708567415,
                    "y": 552.3149501777694
                }
            ]
        },
        {
            "id": "VNhS_b-Od",
            "type": "RECTANGLE",
            "tags": [
                "JIN"
            ],
            "boundingBox": {
                "height": 96.89434851001123,
                "width": 75.40067591292134,
                "left": 1016.113588483146,
                "top": 555.7051205206774
            },
            "points": [
                {
                    "x": 1016.113588483146,
                    "y": 555.7051205206774
                },
                {
                    "x": 1091.5142643960673,
                    "y": 555.7051205206774
                },
                {
                    "x": 1091.5142643960673,
                    "y": 652.5994690306886
                },
                {
                    "x": 1016.113588483146,
                    "y": 652.5994690306886
                }
            ]
        },
        {
            "id": "34DIbSI17",
            "type": "RECTANGLE",
            "tags": [
                "V"
            ],
            "boundingBox": {
                "height": 130.41528027928518,
                "width": 109.7416169241573,
                "left": 799.2357356039325,
                "top": 470.112940622661
            },
            "points": [
                {
                    "x": 799.2357356039325,
                    "y": 470.112940622661
                },
                {
                    "x": 908.9773525280899,
                    "y": 470.112940622661
                },
                {
                    "x": 908.9773525280899,
                    "y": 600.5282209019462
                },
                {
                    "x": 799.2357356039325,
                    "y": 600.5282209019462
                }
            ]
        },
        {
            "id": "Zvsa-xo7A",
            "type": "RECTANGLE",
            "tags": [
                "SUGA"
            ],
            "boundingBox": {
                "height": 109.95452698119387,
                "width": 94.78125,
                "left": 526.8195663623595,
                "top": 511.6157358135292
            },
            "points": [
                {
                    "x": 526.8195663623595,
                    "y": 511.6157358135292
                },
                {
                    "x": 621.6008163623595,
                    "y": 511.6157358135292
                },
                {
                    "x": 621.6008163623595,
                    "y": 621.5702627947231
                },
                {
                    "x": 526.8195663623595,
                    "y": 621.5702627947231
                }
            ]
        },
        {
            "id": "HzKh5Pvn8",
            "type": "RECTANGLE",
            "tags": [
                "J-HOPE"
            ],
            "boundingBox": {
                "height": 141.74284244011977,
                "width": 122.3559295997191,
                "left": 377.0773130266854,
                "top": 415.75712832148207
            },
            "points": [
                {
                    "x": 377.0773130266854,
                    "y": 415.75712832148207
                },
                {
                    "x": 499.4332426264045,
                    "y": 415.75712832148207
                },
                {
                    "x": 499.4332426264045,
                    "y": 557.4999707616018
                },
                {
                    "x": 377.0773130266854,
                    "y": 557.4999707616018
                }
            ]
        }
    ],
    "version": "2.2.0"
}