{
    "asset": {
        "format": "jpg",
        "id": "9408a396d69afe9c59c5fa392e928011",
        "name": "dynamite_2883.jpg",
        "path": "file:/Users/choumasateru/programming/dynamite/dynamite_imgs/dynamite_2883.jpg",
        "size": {
            "width": 1920,
            "height": 1080
        },
        "state": 2,
        "type": 1
    },
    "regions": [
        {
            "id": "3mcIClC20",
            "type": "RECTANGLE",
            "tags": [
                "KOOK"
            ],
            "boundingBox": {
                "height": 617.8720147595434,
                "width": 673.2284936797753,
                "left": 589.8247015449438,
                "top": 128.53359199569613
            },
            "points": [
                {
                    "x": 589.8247015449438,
                    "y": 128.53359199569613
                },
                {
                    "x": 1263.053195224719,
                    "y": 128.53359199569613
                },
                {
                    "x": 1263.053195224719,
                    "y": 746.4056067552395
                },
                {
                    "x": 589.8247015449438,
                    "y": 746.4056067552395
                }
            ]
        },
        {
            "id": "o8lk1rRMS",
            "type": "RECTANGLE",
            "tags": [
                "J-HOPE"
            ],
            "boundingBox": {
                "height": 307.89105626637354,
                "width": 451.43976035814603,
                "left": 0,
                "top": 132.93549132204342
            },
            "points": [
                {
                    "x": 0,
                    "y": 132.93549132204342
                },
                {
                    "x": 451.43976035814603,
                    "y": 132.93549132204342
                },
                {
                    "x": 451.43976035814603,
                    "y": 440.82654758841693
                },
                {
                    "x": 0,
                    "y": 440.82654758841693
                }
            ]
        },
        {
            "id": "RpwOoB0gj",
            "type": "RECTANGLE",
            "tags": [
                "JIMIN"
            ],
            "boundingBox": {
                "height": 312.6839899302957,
                "width": 362.71624824438203,
                "left": 1389.429380266854,
                "top": 131.39727381175152
            },
            "points": [
                {
                    "x": 1389.429380266854,
                    "y": 131.39727381175152
                },
                {
                    "x": 1752.1456285112358,
                    "y": 131.39727381175152
                },
                {
                    "x": 1752.1456285112358,
                    "y": 444.08126374204716
                },
                {
                    "x": 1389.429380266854,
                    "y": 444.08126374204716
                }
            ]
        }
    ],
    "version": "2.2.0"
}