{
    "asset": {
        "format": "jpg",
        "id": "999941866aa0b8bd16f746434f81c093",
        "name": "dynamite_5261.jpg",
        "path": "file:/Users/choumasateru/programming/dynamite/dynamite_imgs/dynamite_5261.jpg",
        "size": {
            "width": 1920,
            "height": 1080
        },
        "state": 2,
        "type": 1
    },
    "regions": [
        {
            "id": "RRO8RfyWb",
            "type": "RECTANGLE",
            "tags": [
                "J-HOPE"
            ],
            "boundingBox": {
                "height": 128.55340544437826,
                "width": 133.21271929824562,
                "left": 1753.961302997076,
                "top": 527.4297746628574
            },
            "points": [
                {
                    "x": 1753.961302997076,
                    "y": 527.4297746628574
                },
                {
                    "x": 1887.1740222953215,
                    "y": 527.4297746628574
                },
                {
                    "x": 1887.1740222953215,
                    "y": 655.9831801072357
                },
                {
                    "x": 1753.961302997076,
                    "y": 655.9831801072357
                }
            ]
        },
        {
            "id": "HW0d_5EfG",
            "type": "RECTANGLE",
            "tags": [
                "JIMIN"
            ],
            "boundingBox": {
                "height": 133.3748992972812,
                "width": 155.5286001461988,
                "left": 1535.500730994152,
                "top": 481.78072448413127
            },
            "points": [
                {
                    "x": 1535.500730994152,
                    "y": 481.78072448413127
                },
                {
                    "x": 1691.0293311403507,
                    "y": 481.78072448413127
                },
                {
                    "x": 1691.0293311403507,
                    "y": 615.1556237814125
                },
                {
                    "x": 1535.500730994152,
                    "y": 615.1556237814125
                }
            ]
        },
        {
            "id": "bvSVfXB8T",
            "type": "RECTANGLE",
            "tags": [
                "RM"
            ],
            "boundingBox": {
                "height": 120.73789917203747,
                "width": 107.49337536549707,
                "left": 1169.7066885964912,
                "top": 463.7580435238843
            },
            "points": [
                {
                    "x": 1169.7066885964912,
                    "y": 463.7580435238843
                },
                {
                    "x": 1277.2000639619882,
                    "y": 463.7580435238843
                },
                {
                    "x": 1277.2000639619882,
                    "y": 584.4959426959218
                },
                {
                    "x": 1169.7066885964912,
                    "y": 584.4959426959218
                }
            ]
        },
        {
            "id": "wQodShSBI",
            "type": "RECTANGLE",
            "tags": [
                "V"
            ],
            "boundingBox": {
                "height": 192.3651979866226,
                "width": 183.93366228070175,
                "left": 762.0200566520467,
                "top": 385.4313313237922
            },
            "points": [
                {
                    "x": 762.0200566520467,
                    "y": 385.4313313237922
                },
                {
                    "x": 945.9537189327485,
                    "y": 385.4313313237922
                },
                {
                    "x": 945.9537189327485,
                    "y": 577.7965293104148
                },
                {
                    "x": 762.0200566520467,
                    "y": 577.7965293104148
                }
            ]
        },
        {
            "id": "FBCyCDnk7",
            "type": "RECTANGLE",
            "tags": [
                "SUGA"
            ],
            "boundingBox": {
                "height": 115.3001237204831,
                "width": 100.24688185307016,
                "left": 633.9900287828947,
                "top": 526.7970992539537
            },
            "points": [
                {
                    "x": 633.9900287828947,
                    "y": 526.7970992539537
                },
                {
                    "x": 734.2369106359648,
                    "y": 526.7970992539537
                },
                {
                    "x": 734.2369106359648,
                    "y": 642.0972229744367
                },
                {
                    "x": 633.9900287828947,
                    "y": 642.0972229744367
                }
            ]
        },
        {
            "id": "BVfaV3exZ",
            "type": "RECTANGLE",
            "tags": [
                "JIN"
            ],
            "boundingBox": {
                "height": 145.49986417826582,
                "width": 135.47286184210526,
                "left": 279.58024945175436,
                "top": 466.53773686294954
            },
            "points": [
                {
                    "x": 279.58024945175436,
                    "y": 466.53773686294954
                },
                {
                    "x": 415.0531112938596,
                    "y": 466.53773686294954
                },
                {
                    "x": 415.0531112938596,
                    "y": 612.0376010412153
                },
                {
                    "x": 279.58024945175436,
                    "y": 612.0376010412153
                }
            ]
        },
        {
            "id": "ldk5aS5im",
            "type": "RECTANGLE",
            "tags": [
                "KOOK"
            ],
            "boundingBox": {
                "height": 108.32692799163236,
                "width": 66.18058411001462,
                "left": 0,
                "top": 501.70440197817373
            },
            "points": [
                {
                    "x": 0,
                    "y": 501.70440197817373
                },
                {
                    "x": 66.18058411001462,
                    "y": 501.70440197817373
                },
                {
                    "x": 66.18058411001462,
                    "y": 610.031329969806
                },
                {
                    "x": 0,
                    "y": 610.031329969806
                }
            ]
        }
    ],
    "version": "2.2.0"
}