{
    "asset": {
        "format": "jpg",
        "id": "a2a2dca60bd3637ae47e8dfdb87a700e",
        "name": "dynamite_3360.jpg",
        "path": "file:/Users/choumasateru/programming/dynamite/dynamite_imgs/dynamite_3360.jpg",
        "size": {
            "width": 1920,
            "height": 1080
        },
        "state": 2,
        "type": 1
    },
    "regions": [
        {
            "id": "c3byy_iX-",
            "type": "RECTANGLE",
            "tags": [
                "KOOK"
            ],
            "boundingBox": {
                "height": 78.03522570379849,
                "width": 68.66107692774005,
                "left": 881.6962445441319,
                "top": 352.4044505152209
            },
            "points": [
                {
                    "x": 881.6962445441319,
                    "y": 352.4044505152209
                },
                {
                    "x": 950.357321471872,
                    "y": 352.4044505152209
                },
                {
                    "x": 950.357321471872,
                    "y": 430.43967621901936
                },
                {
                    "x": 881.6962445441319,
                    "y": 430.43967621901936
                }
            ]
        },
        {
            "id": "UbFOZpW6T",
            "type": "RECTANGLE",
            "tags": [
                "V"
            ],
            "boundingBox": {
                "height": 70.87261331492456,
                "width": 68.57207807953444,
                "left": 773.8961339112511,
                "top": 359.0372188173491
            },
            "points": [
                {
                    "x": 773.8961339112511,
                    "y": 359.0372188173491
                },
                {
                    "x": 842.4682119907856,
                    "y": 359.0372188173491
                },
                {
                    "x": 842.4682119907856,
                    "y": 429.9098321322737
                },
                {
                    "x": 773.8961339112511,
                    "y": 429.9098321322737
                }
            ]
        }
    ],
    "version": "2.2.0"
}