{
    "asset": {
        "format": "jpg",
        "id": "b6ac6edbd8a2fe33a1e29af33fdc3cb8",
        "name": "dynamite_4595.jpg",
        "path": "file:/Users/choumasateru/programming/dynamite/dynamite_imgs/dynamite_4595.jpg",
        "size": {
            "width": 1920,
            "height": 1080
        },
        "state": 2,
        "type": 1
    },
    "regions": [
        {
            "id": "U8RhDgWNh",
            "type": "RECTANGLE",
            "tags": [
                "KOOK"
            ],
            "boundingBox": {
                "height": 124.42959910425647,
                "width": 120.04694319835112,
                "left": 1523.324859056741,
                "top": 367.70554535964436
            },
            "points": [
                {
                    "x": 1523.324859056741,
                    "y": 367.70554535964436
                },
                {
                    "x": 1643.371802255092,
                    "y": 367.70554535964436
                },
                {
                    "x": 1643.371802255092,
                    "y": 492.1351444639009
                },
                {
                    "x": 1523.324859056741,
                    "y": 492.1351444639009
                }
            ]
        },
        {
            "id": "nDvzl6Ttf",
            "type": "RECTANGLE",
            "tags": [
                "V"
            ],
            "boundingBox": {
                "height": 132.94836004849137,
                "width": 136.89989239815714,
                "left": 1314.5593628758486,
                "top": 378.7388495083513
            },
            "points": [
                {
                    "x": 1314.5593628758486,
                    "y": 378.7388495083513
                },
                {
                    "x": 1451.4592552740057,
                    "y": 378.7388495083513
                },
                {
                    "x": 1451.4592552740057,
                    "y": 511.6872095568427
                },
                {
                    "x": 1314.5593628758486,
                    "y": 511.6872095568427
                }
            ]
        },
        {
            "id": "6TzOMvoKF",
            "type": "RECTANGLE",
            "tags": [
                "JIN"
            ],
            "boundingBox": {
                "height": 113.55091805293642,
                "width": 109.06166646459748,
                "left": 1038.190432529098,
                "top": 361.0769253434806
            },
            "points": [
                {
                    "x": 1038.190432529098,
                    "y": 361.0769253434806
                },
                {
                    "x": 1147.2520989936954,
                    "y": 361.0769253434806
                },
                {
                    "x": 1147.2520989936954,
                    "y": 474.627843396417
                },
                {
                    "x": 1038.190432529098,
                    "y": 474.627843396417
                }
            ]
        },
        {
            "id": "RdltiptXh",
            "type": "RECTANGLE",
            "tags": [
                "JIMIN"
            ],
            "boundingBox": {
                "height": 155.17385338092672,
                "width": 161.11860451018427,
                "left": 772.0836490664403,
                "top": 399.3612860317888
            },
            "points": [
                {
                    "x": 772.0836490664403,
                    "y": 399.3612860317888
                },
                {
                    "x": 933.2022535766246,
                    "y": 399.3612860317888
                },
                {
                    "x": 933.2022535766246,
                    "y": 554.5351394127155
                },
                {
                    "x": 772.0836490664403,
                    "y": 554.5351394127155
                }
            ]
        },
        {
            "id": "OfBnBc8wt",
            "type": "RECTANGLE",
            "tags": [
                "J-HOPE"
            ],
            "boundingBox": {
                "height": 138.90995841190733,
                "width": 151.34526930771096,
                "left": 181.57333596023278,
                "top": 432.2892435008082
            },
            "points": [
                {
                    "x": 181.57333596023278,
                    "y": 432.2892435008082
                },
                {
                    "x": 332.91860526794375,
                    "y": 432.2892435008082
                },
                {
                    "x": 332.91860526794375,
                    "y": 571.1992019127155
                },
                {
                    "x": 181.57333596023278,
                    "y": 571.1992019127155
                }
            ]
        }
    ],
    "version": "2.2.0"
}