{
    "asset": {
        "format": "jpg",
        "id": "b90d56bcc1ed76da566b10707c3668a7",
        "name": "dynamite_3772.jpg",
        "path": "file:/Users/choumasateru/programming/dynamite/dynamite_imgs/dynamite_3772.jpg",
        "size": {
            "width": 1920,
            "height": 1080
        },
        "state": 2,
        "type": 1
    },
    "regions": [
        {
            "id": "S8a4MvWTR",
            "type": "RECTANGLE",
            "tags": [
                "JIMIN"
            ],
            "boundingBox": {
                "height": 69.05793709590517,
                "width": 50.58976418525703,
                "left": 855.4684090082444,
                "top": 590.9985730401401
            },
            "points": [
                {
                    "x": 855.4684090082444,
                    "y": 590.9985730401401
                },
                {
                    "x": 906.0581731935014,
                    "y": 590.9985730401401
                },
                {
                    "x": 906.0581731935014,
                    "y": 660.0565101360453
                },
                {
                    "x": 855.4684090082444,
                    "y": 660.0565101360453
                }
            ]
        },
        {
            "id": "vuuPr0Sf2",
            "type": "RECTANGLE",
            "tags": [
                "KOOK"
            ],
            "boundingBox": {
                "height": 53.75826289735991,
                "width": 57.21352903734238,
                "left": 615.6232192652764,
                "top": 583.343678441541
            },
            "points": [
                {
                    "x": 615.6232192652764,
                    "y": 583.343678441541
                },
                {
                    "x": 672.8367483026188,
                    "y": 583.343678441541
                },
                {
                    "x": 672.8367483026188,
                    "y": 637.1019413389008
                },
                {
                    "x": 615.6232192652764,
                    "y": 637.1019413389008
                }
            ]
        }
    ],
    "version": "2.2.0"
}