{
    "asset": {
        "format": "jpg",
        "id": "e9d87c2351597b248d67176735cda43d",
        "name": "dynamite_3476.jpg",
        "path": "file:/Users/choumasateru/programming/dynamite/dynamite_imgs/dynamite_3476.jpg",
        "size": {
            "width": 1920,
            "height": 1080
        },
        "state": 2,
        "type": 1
    },
    "regions": [
        {
            "id": "UahOB2mfr",
            "type": "RECTANGLE",
            "tags": [
                "SUGA"
            ],
            "boundingBox": {
                "height": 109.23607556573276,
                "width": 93.89901339718719,
                "left": 1556.4856253031037,
                "top": 549.2037395608836
            },
            "points": [
                {
                    "x": 1556.4856253031037,
                    "y": 549.2037395608836
                },
                {
                    "x": 1650.384638700291,
                    "y": 549.2037395608836
                },
                {
                    "x": 1650.384638700291,
                    "y": 658.4398151266164
                },
                {
                    "x": 1556.4856253031037,
                    "y": 658.4398151266164
                }
            ]
        },
        {
            "id": "VmHEetOD5",
            "type": "RECTANGLE",
            "tags": [
                "J-HOPE"
            ],
            "boundingBox": {
                "height": 118.67030071390086,
                "width": 130.1263185014549,
                "left": 1442.7948820926285,
                "top": 431.0100939520474
            },
            "points": [
                {
                    "x": 1442.7948820926285,
                    "y": 431.0100939520474
                },
                {
                    "x": 1572.9212005940833,
                    "y": 431.0100939520474
                },
                {
                    "x": 1572.9212005940833,
                    "y": 549.6803946659483
                },
                {
                    "x": 1442.7948820926285,
                    "y": 549.6803946659483
                }
            ]
        },
        {
            "id": "ISs4Lsted",
            "type": "RECTANGLE",
            "tags": [
                "JIMIN"
            ],
            "boundingBox": {
                "height": 107.10374292834051,
                "width": 84.69905583171678,
                "left": 1184.9059999393792,
                "top": 542.614329370959
            },
            "points": [
                {
                    "x": 1184.9059999393792,
                    "y": 542.614329370959
                },
                {
                    "x": 1269.605055771096,
                    "y": 542.614329370959
                },
                {
                    "x": 1269.605055771096,
                    "y": 649.7180722992996
                },
                {
                    "x": 1184.9059999393792,
                    "y": 649.7180722992996
                }
            ]
        },
        {
            "id": "meIuPxKeT",
            "type": "RECTANGLE",
            "tags": [
                "JIN"
            ],
            "boundingBox": {
                "height": 123.57999604323814,
                "width": 116.45857329049466,
                "left": 941.1814606571289,
                "top": 340.0729601629849
            },
            "points": [
                {
                    "x": 941.1814606571289,
                    "y": 340.0729601629849
                },
                {
                    "x": 1057.6400339476236,
                    "y": 340.0729601629849
                },
                {
                    "x": 1057.6400339476236,
                    "y": 463.65295620622305
                },
                {
                    "x": 941.1814606571289,
                    "y": 463.65295620622305
                }
            ]
        },
        {
            "id": "UbYRvABsT",
            "type": "RECTANGLE",
            "tags": [
                "V"
            ],
            "boundingBox": {
                "height": 130.0123396248653,
                "width": 107.10312348448109,
                "left": 656.7251151794375,
                "top": 444.24068266769933
            },
            "points": [
                {
                    "x": 656.7251151794375,
                    "y": 444.24068266769933
                },
                {
                    "x": 763.8282386639185,
                    "y": 444.24068266769933
                },
                {
                    "x": 763.8282386639185,
                    "y": 574.2530222925647
                },
                {
                    "x": 656.7251151794375,
                    "y": 574.2530222925647
                }
            ]
        },
        {
            "id": "EKokifauW",
            "type": "RECTANGLE",
            "tags": [
                "RM"
            ],
            "boundingBox": {
                "height": 118.45066886112608,
                "width": 105.91902961323957,
                "left": 457.2565887184772,
                "top": 483.88454463564113
            },
            "points": [
                {
                    "x": 457.2565887184772,
                    "y": 483.88454463564113
                },
                {
                    "x": 563.1756183317168,
                    "y": 483.88454463564113
                },
                {
                    "x": 563.1756183317168,
                    "y": 602.3352134967672
                },
                {
                    "x": 457.2565887184772,
                    "y": 602.3352134967672
                }
            ]
        }
    ],
    "version": "2.2.0"
}