{
    "asset": {
        "format": "jpg",
        "id": "f54811855b5030c331e133c8ed60106d",
        "name": "dynamite_3695.jpg",
        "path": "file:/Users/choumasateru/programming/dynamite/dynamite_imgs/dynamite_3695.jpg",
        "size": {
            "width": 1920,
            "height": 1080
        },
        "state": 2,
        "type": 1
    },
    "regions": [
        {
            "id": "uhjAXzsc8",
            "type": "RECTANGLE",
            "tags": [
                "JIN"
            ],
            "boundingBox": {
                "height": 116.3442488045528,
                "width": 93.5815500727449,
                "left": 1410.0559226479145,
                "top": 529.5962692786907
            },
            "points": [
                {
                    "x": 1410.0559226479145,
                    "y": 529.5962692786907
                },
                {
                    "x": 1503.6374727206594,
                    "y": 529.5962692786907
                },
                {
                    "x": 1503.6374727206594,
                    "y": 645.9405180832435
                },
                {
                    "x": 1410.0559226479145,
                    "y": 645.9405180832435
                }
            ]
        },
        {
            "id": "cVVijSGnn",
            "type": "RECTANGLE",
            "tags": [
                "J-HOPE"
            ],
            "boundingBox": {
                "height": 125.1367397966056,
                "width": 99.34874363482056,
                "left": 1155.6580004243453,
                "top": 520.6553492052801
            },
            "points": [
                {
                    "x": 1155.6580004243453,
                    "y": 520.6553492052801
                },
                {
                    "x": 1255.0067440591658,
                    "y": 520.6553492052801
                },
                {
                    "x": 1255.0067440591658,
                    "y": 645.7920890018858
                },
                {
                    "x": 1155.6580004243453,
                    "y": 645.7920890018858
                }
            ]
        },
        {
            "id": "GzAGolS4H",
            "type": "RECTANGLE",
            "tags": [
                "V"
            ],
            "boundingBox": {
                "height": 116.73918835870151,
                "width": 104.48044222841901,
                "left": 953.9230722599418,
                "top": 512.949936439251
            },
            "points": [
                {
                    "x": 953.9230722599418,
                    "y": 512.949936439251
                },
                {
                    "x": 1058.4035144883608,
                    "y": 512.949936439251
                },
                {
                    "x": 1058.4035144883608,
                    "y": 629.6891247979526
                },
                {
                    "x": 953.9230722599418,
                    "y": 629.6891247979526
                }
            ]
        },
        {
            "id": "L840KrcII",
            "type": "RECTANGLE",
            "tags": [
                "RM"
            ],
            "boundingBox": {
                "height": 102.5063055630388,
                "width": 83.54218446896216,
                "left": 721.6469901794375,
                "top": 523.3771930563039
            },
            "points": [
                {
                    "x": 721.6469901794375,
                    "y": 523.3771930563039
                },
                {
                    "x": 805.1891746483996,
                    "y": 523.3771930563039
                },
                {
                    "x": 805.1891746483996,
                    "y": 625.8834986193426
                },
                {
                    "x": 721.6469901794375,
                    "y": 625.8834986193426
                }
            ]
        },
        {
            "id": "BP192Agtf",
            "type": "RECTANGLE",
            "tags": [
                "SUGA"
            ],
            "boundingBox": {
                "height": 101.96992650525323,
                "width": 91.54764791464598,
                "left": 531.1518890943258,
                "top": 543.1259323646282
            },
            "points": [
                {
                    "x": 531.1518890943258,
                    "y": 543.1259323646282
                },
                {
                    "x": 622.6995370089719,
                    "y": 543.1259323646282
                },
                {
                    "x": 622.6995370089719,
                    "y": 645.0958588698815
                },
                {
                    "x": 531.1518890943258,
                    "y": 645.0958588698815
                }
            ]
        }
    ],
    "version": "2.2.0"
}