{
    "asset": {
        "format": "jpg",
        "id": "ffe81bca3b97182d7196141bc8da623d",
        "name": "dynamite_0280.jpg",
        "path": "file:/Users/choumasateru/programming/dynamite/dynamite_imgs/dynamite_0280.jpg",
        "size": {
            "width": 1920,
            "height": 1080
        },
        "state": 2,
        "type": 1
    },
    "regions": [
        {
            "id": "K0sLlMN8x",
            "type": "RECTANGLE",
            "tags": [
                "RM"
            ],
            "boundingBox": {
                "height": 141.6374556515195,
                "width": 143.32067530959753,
                "left": 1367.7263931888544,
                "top": 251.9878243262615
            },
            "points": [
                {
                    "x": 1367.7263931888544,
                    "y": 251.9878243262615
                },
                {
                    "x": 1511.047068498452,
                    "y": 251.9878243262615
                },
                {
                    "x": 1511.047068498452,
                    "y": 393.62527997778096
                },
                {
                    "x": 1367.7263931888544,
                    "y": 393.62527997778096
                }
            ]
        },
        {
            "id": "YO44BK-dL",
            "type": "RECTANGLE",
            "tags": [
                "SUGA"
            ],
            "boundingBox": {
                "height": 161.22894119122708,
                "width": 154.7295859133127,
                "left": 360.07425503095976,
                "top": 317.45265239750574
            },
            "points": [
                {
                    "x": 360.07425503095976,
                    "y": 317.45265239750574
                },
                {
                    "x": 514.8038409442725,
                    "y": 317.45265239750574
                },
                {
                    "x": 514.8038409442725,
                    "y": 478.6815935887328
                },
                {
                    "x": 360.07425503095976,
                    "y": 478.6815935887328
                }
            ]
        },
        {
            "id": "wDGw23M6l",
            "type": "RECTANGLE",
            "tags": [
                "J-HOPE"
            ],
            "boundingBox": {
                "height": 138.56833921659978,
                "width": 108.46519446594428,
                "left": 1287.5489792956657,
                "top": 354.4245896645642
            },
            "points": [
                {
                    "x": 1287.5489792956657,
                    "y": 354.4245896645642
                },
                {
                    "x": 1396.01417376161,
                    "y": 354.4245896645642
                },
                {
                    "x": 1396.01417376161,
                    "y": 492.992928881164
                },
                {
                    "x": 1287.5489792956657,
                    "y": 492.992928881164
                }
            ]
        },
        {
            "id": "IOUfyu3yl",
            "type": "RECTANGLE",
            "tags": [
                "JIN"
            ],
            "boundingBox": {
                "height": 147.95947265625,
                "width": 118.65264609133126,
                "left": 792.343508126935,
                "top": 334.9206117402523
            },
            "points": [
                {
                    "x": 792.343508126935,
                    "y": 334.9206117402523
                },
                {
                    "x": 910.9961542182663,
                    "y": 334.9206117402523
                },
                {
                    "x": 910.9961542182663,
                    "y": 482.8800843965023
                },
                {
                    "x": 792.343508126935,
                    "y": 482.8800843965023
                }
            ]
        },
        {
            "id": "u0cfN1Cbz",
            "type": "RECTANGLE",
            "tags": [
                "KOOK"
            ],
            "boundingBox": {
                "height": 148.00682473838876,
                "width": 142.8704285990712,
                "left": 1027.781782120743,
                "top": 288.27016287987385
            },
            "points": [
                {
                    "x": 1027.781782120743,
                    "y": 288.27016287987385
                },
                {
                    "x": 1170.6522107198143,
                    "y": 288.27016287987385
                },
                {
                    "x": 1170.6522107198143,
                    "y": 436.27698761826264
                },
                {
                    "x": 1027.781782120743,
                    "y": 436.27698761826264
                }
            ]
        },
        {
            "id": "HCS2WRivU",
            "type": "RECTANGLE",
            "tags": [
                "V"
            ],
            "boundingBox": {
                "height": 179.25399808271217,
                "width": 161.00582914086687,
                "left": 647.8543440402477,
                "top": 302.03752374211587
            },
            "points": [
                {
                    "x": 647.8543440402477,
                    "y": 302.03752374211587
                },
                {
                    "x": 808.8601731811145,
                    "y": 302.03752374211587
                },
                {
                    "x": 808.8601731811145,
                    "y": 481.291521824828
                },
                {
                    "x": 647.8543440402477,
                    "y": 481.291521824828
                }
            ]
        }
    ],
    "version": "2.2.0"
}